{"structures":[{"id":753204,"panels":[{"tabID":30666046,"panelID":1172351,"panelNumber":93071,"hoverText":"Olive Hwy NL 700' e/o Skyline Dr FW","heading":"W","weeklyImpressions":36491,"productType":"BULLETINS"},{"tabID":30666045,"panelID":1172352,"panelNumber":93072,"hoverText":"Olive Hwy NL 700' e/o Skyline Dr FE","heading":"E","weeklyImpressions":34242,"productType":"BULLETINS"}],"lat":39.510783,"long":-121.486750,"cbsaName":null,"cbsaGUID":null,"plantId":1003262551},{"id":753263,"panels":[{"tabID":30666283,"panelID":1172463,"panelNumber":32191,"hoverText":"Oro Dam Blvd SL 100' e/o Orange Ave Junction FE","heading":"E","weeklyImpressions":41016,"productType":"POSTERS"}],"lat":39.517867,"long":-121.533050,"cbsaName":null,"cbsaGUID":null,"plantId":1003262551},{"id":753311,"panels":[{"tabID":30666169,"panelID":1172566,"panelNumber":83021,"hoverText":"Grand Ave SL 350' e/o Hwy 70 FE","heading":"E","weeklyImpressions":22762,"productType":"JR POSTERS"},{"tabID":30666170,"panelID":1172567,"panelNumber":83022,"hoverText":"Grand Ave SL 350' e/o Hwy 70 FE","heading":"E","weeklyImpressions":22438,"productType":"JR POSTERS"},{"tabID":30666171,"panelID":1172568,"panelNumber":83023,"hoverText":"Grand Ave SL 350' e/o Hwy 70 FW","heading":"W","weeklyImpressions":31504,"productType":"JR POSTERS"},{"tabID":30666172,"panelID":1172569,"panelNumber":83024,"hoverText":"Grand Ave SL 350' e/o Hwy 70 FW","heading":"W","weeklyImpressions":31504,"productType":"JR POSTERS"}],"lat":39.519867,"long":-121.570620,"cbsaName":null,"cbsaGUID":null,"plantId":1003262551},{"id":753312,"panels":[{"tabID":30666174,"panelID":1172570,"panelNumber":83031,"hoverText":"Grand Ave NL 450' w/o Tehama FW","heading":"W","weeklyImpressions":9087,"productType":"JR POSTERS"},{"tabID":30666173,"panelID":1172571,"panelNumber":83032,"hoverText":"Grand Ave NL 450' w/o Tehama FE","heading":"E","weeklyImpressions":12635,"productType":"JR POSTERS"}],"lat":39.514400,"long":-121.586170,"cbsaName":null,"cbsaGUID":null,"plantId":1003262551},{"id":753313,"panels":[{"tabID":30666181,"panelID":1172572,"panelNumber":83111,"hoverText":"Washington Ave WL at Montgomery (wall) FN","heading":"N","weeklyImpressions":58441,"productType":"JR POSTERS"},{"tabID":30666182,"panelID":1172573,"panelNumber":83112,"hoverText":"Washington Ave WL at Montgomery (wall) FN","heading":"N","weeklyImpressions":76656,"productType":"JR POSTERS"}],"lat":39.515867,"long":-121.549780,"cbsaName":null,"cbsaGUID":null,"plantId":1003262551},{"id":753360,"panels":[{"tabID":30666028,"panelID":1172665,"panelNumber":31431,"hoverText":"Hwy 70 WL 200' n/o Grand Ave Overpass FN","heading":"N","weeklyImpressions":23551,"productType":"Digital"}],"lat":39.519933,"long":-121.572870,"cbsaName":null,"cbsaGUID":null,"plantId":1003262551},{"id":753373,"panels":[{"tabID":30666041,"panelID":1172696,"panelNumber":92091,"hoverText":"Olive Hwy NL 400' e/o Skyline Dr FW","heading":"W","weeklyImpressions":35815,"productType":"BULLETINS"},{"tabID":30666040,"panelID":1172697,"panelNumber":92092,"hoverText":"Olive Hwy NL 400' e/o Skyline Dr FE","heading":"E","weeklyImpressions":38948,"productType":"BULLETINS"}],"lat":39.510550,"long":-121.487630,"cbsaName":null,"cbsaGUID":null,"plantId":1003262551},{"id":753489,"panels":[{"tabID":30666566,"panelID":1172913,"panelNumber":99011,"hoverText":"I-5 WL 2 miles n/o Willows I-5/Hwy 162 Interchange FN","heading":"N","weeklyImpressions":35728,"productType":"BULLETINS"}],"lat":39.553467,"long":-122.217533,"cbsaName":null,"cbsaGUID":null,"plantId":1003262551},{"id":753893,"panels":[{"tabID":0,"panelID":1174416,"panelNumber":2001,"hoverText":"West side of Table Mountain Blvd, 250' north of Grand Ave\n","heading":"NW","weeklyImpressions":null,"productType":"SHELTERS"},{"tabID":0,"panelID":1174417,"panelNumber":2002,"hoverText":"West side of Table Mountain Blvd, 250' north of Grand Ave\n","heading":"SE","weeklyImpressions":null,"productType":"SHELTERS"}],"lat":39.522449,"long":-121.556366,"cbsaName":null,"cbsaGUID":null,"plantId":1003273335},{"id":753894,"panels":[{"tabID":0,"panelID":1174418,"panelNumber":2011,"hoverText":"East side of Table Mountain Blvd, 70' north of Grand Ave\n","heading":"SE","weeklyImpressions":null,"productType":"SHELTERS"},{"tabID":0,"panelID":1174419,"panelNumber":2012,"hoverText":"East side of Table Mountain Blvd, 70' north of Grand Ave\n","heading":"NW","weeklyImpressions":null,"productType":"SHELTERS"}],"lat":39.522182,"long":-121.555550,"cbsaName":null,"cbsaGUID":null,"plantId":1003273335}],"shapes":[{"points":[{"lat":40.03780743585841,"long":-120.80697547363282},{"lat":39.5534999939626,"long":-120.80697547363282},{"lat":39.5534999939626,"long":-122.89300452636719},{"lat":40.03780743585841,"long":-122.89300452636719}]},{"points":[{"lat":40.03780743585841,"long":-120.80697547363282},{"lat":39.5534999939626,"long":-120.80697547363282},{"lat":39.5534999939626,"long":-122.89300452636719},{"lat":40.03780743585841,"long":-122.89300452636719}]},{"points":[{"lat":40.03780743585841,"long":-120.80697547363282},{"lat":39.5534999939626,"long":-120.80697547363282},{"lat":39.5534999939626,"long":-122.89300452636719},{"lat":40.03780743585841,"long":-122.89300452636719}]},{"points":[{"lat":40.03780743585841,"long":-120.80697547363282},{"lat":39.5534999939626,"long":-120.80697547363282},{"lat":39.5534999939626,"long":-122.89300452636719},{"lat":40.03780743585841,"long":-122.89300452636719}]},{"points":[{"lat":40.03780743585841,"long":-120.80697547363282},{"lat":39.5534999939626,"long":-120.80697547363282},{"lat":39.5534999939626,"long":-122.89300452636719},{"lat":40.03780743585841,"long":-122.89300452636719}]},{"points":[{"lat":40.03780743585841,"long":-120.80697547363282},{"lat":39.5534999939626,"long":-120.80697547363282},{"lat":39.5534999939626,"long":-122.89300452636719},{"lat":40.03780743585841,"long":-122.89300452636719}]},{"points":[{"lat":40.03780743585841,"long":-120.80697547363282},{"lat":39.508620958214465,"long":-120.80697547363282},{"lat":39.508620958214465,"long":-123.27472794928478},{"lat":40.03780743585841,"long":-123.27472794928478}]}]}